crispy_daisyui/__init__.py
crispy_daisyui/daisyui.py
crispy_daisyui/layout.py
crispy_daisyui/templates/daisyui/display_form.html
crispy_daisyui/templates/daisyui/errors.html
crispy_daisyui/templates/daisyui/errors_formset.html
crispy_daisyui/templates/daisyui/field.html
crispy_daisyui/templates/daisyui/inputs.html
crispy_daisyui/templates/daisyui/table_inline_formset.html
crispy_daisyui/templates/daisyui/uni_form.html
crispy_daisyui/templates/daisyui/uni_formset.html
crispy_daisyui/templates/daisyui/whole_uni_form.html
crispy_daisyui/templates/daisyui/whole_uni_formset.html
crispy_daisyui/templates/daisyui/layout/alert.html
crispy_daisyui/templates/daisyui/layout/baseinput.html
crispy_daisyui/templates/daisyui/layout/button.html
crispy_daisyui/templates/daisyui/layout/checkbox.html
crispy_daisyui/templates/daisyui/layout/checkboxselectmultiple.html
crispy_daisyui/templates/daisyui/layout/column.html
crispy_daisyui/templates/daisyui/layout/div.html
crispy_daisyui/templates/daisyui/layout/field_errors.html
crispy_daisyui/templates/daisyui/layout/field_errors_block.html
crispy_daisyui/templates/daisyui/layout/field_with_buttons.html
crispy_daisyui/templates/daisyui/layout/fieldset.html
crispy_daisyui/templates/daisyui/layout/formactions.html
crispy_daisyui/templates/daisyui/layout/help_text.html
crispy_daisyui/templates/daisyui/layout/help_text_and_errors.html
crispy_daisyui/templates/daisyui/layout/inline_field.html
crispy_daisyui/templates/daisyui/layout/prepended_appended_text.html
crispy_daisyui/templates/daisyui/layout/radioselect.html
crispy_daisyui/templates/daisyui/layout/radioselect_inline.html
crispy_daisyui/templates/daisyui/layout/row.html
crispy_daisyui/templates/daisyui/layout/select.html
crispy_daisyui/templates/daisyui/layout/select_option.html
crispy_daisyui/templates/daisyui/layout/toggle.html
crispy_daisyui/templatetags/__init__.py
crispy_daisyui/templatetags/daisyui_field.py
crispy_daisyui/templatetags/daisyui_filters.py
crispy_daisyui-0.9.0.dist-info/licenses/LICENSE
crispy_daisyui-0.9.0.dist-info/METADATA
crispy_daisyui-0.9.0.dist-info/WHEEL
crispy_daisyui-0.9.0.dist-info/top_level.txt
crispy_daisyui-0.9.0.dist-info/RECORD
