Metadata-Version: 2.4
Name: crispy-daisyui
Version: 0.9.0
Summary: A DaisyUI package for Django Crispy Forms
Author: Fabian Geiger
License: Apache-2.0
Project-URL: Homepage, https://github.com/fabge/crispy-daisyui
Project-URL: Changelog, https://github.com/fabge/crispy-daisyui/releases
Project-URL: Issues, https://github.com/fabge/crispy-daisyui/issues
Project-URL: CI, https://github.com/fabge/crispy-daisyui/actions
Keywords: forms,django,crispy,tailwind,daisyui
Classifier: License :: OSI Approved :: Apache Software License
Requires-Python: >=3.7
License-File: LICENSE
Requires-Dist: django-crispy-forms>=1.11.2
Requires-Dist: django>=3.2
Dynamic: license-file
